heat1d/__init__.py
heat1d/cli.py
heat1d/main.py
heat1d/orbits.py
heat1d/plotting.py
heat1d-0.3.2.dist-info/AUTHORS.rst
heat1d-0.3.2.dist-info/METADATA
heat1d-0.3.2.dist-info/WHEEL
heat1d-0.3.2.dist-info/entry_points.txt
heat1d-0.3.2.dist-info/top_level.txt
heat1d-0.3.2.dist-info/RECORD
