Metadata-Version: 2.1
Name: heat1d
Version: 0.3.2
Summary: Thermal model for planetary science applications
Home-page: https://github.com/phayne/heat1d
Author: Paul O. Hayne
Author-email: paul.hayne@lasp.colorado.edu
Maintainer-email: kmichael.aye@gmail.com
License: MIT license
Keywords: heat1d
Platform: UNKNOWN
Classifier: Development Status :: 4 - Beta
Classifier: Intended Audience :: Science/Research
Classifier: License :: OSI Approved :: MIT License
Classifier: Natural Language :: English
Classifier: Programming Language :: Python :: 3
Classifier: Programming Language :: Python :: 3.7
Requires-Dist: Click (>=6.0)
Requires-Dist: numpy
Requires-Dist: matplotlib
Requires-Dist: planets (>=0.4.6)
